DataUtilsForpip/StockDataUtils.py
DataUtilsForpip/__init__.py
datautilsforpip-999.999.999.dist-info/LICENSE
datautilsforpip-999.999.999.dist-info/METADATA
datautilsforpip-999.999.999.dist-info/WHEEL
datautilsforpip-999.999.999.dist-info/top_level.txt
datautilsforpip-999.999.999.dist-info/RECORD
