Metadata-Version: 2.2
Name: DataUtilsForPiP
Version: 999.999.999
Summary: Utils for Stock-Clock
Author: Qi Yueran
Author-email: 1206585163@qq.com
Classifier: Programming Language :: Python :: 3
Classifier: License :: OSI Approved :: MIT License
Classifier: Operating System :: OS Independent
Requires-Python: >=3.10
License-File: LICENSE
Dynamic: author
Dynamic: author-email
Dynamic: classifier
Dynamic: description
Dynamic: description-content-type
Dynamic: requires-python
Dynamic: summary
